msph/__init__.py
msph/__main__.py
msph/app.py
msph/config.py
msph/exceptions.py
msph/models.py
msph/settings.py
msph/utils.py
msph/validators.py
msph/workspace.py
msph/clients/__init__.py
msph/clients/constants.py
msph/clients/framework.py
msph/clients/graph_api.py
msph/clients/ms_online.py
msph/commands/__init__.py
msph/commands/root.py
msph/commands/auth/__init__.py
msph/commands/auth/root.py
msph/commands/auth/phish/__init__.py
msph/commands/auth/phish/command.py
msph/commands/auth/phish/msgs.py
msph/commands/auth/refresh/__init__.py
msph/commands/auth/refresh/command.py
msph/commands/auth/refresh/msgs.py
msph/commands/dump/__init__.py
msph/commands/dump/root.py
msph/commands/dump/email/__init__.py
msph/commands/dump/email/command.py
msph/commands/dump/email/msgs.py
msph/commands/export/__init__.py
msph/commands/export/command.py
msph/commands/export/msgs.py
msph/commands/switch/__init__.py
msph/commands/switch/command.py
msph/commands/switch/msgs.py
msph/commands/target/__init__.py
msph/commands/target/command.py
msph/commands/target/msgs.py
msph/commands/target/validators.py
msph/commands/wsp/__init__.py
msph/commands/wsp/command.py
msph/commands/wsp/msgs.py
msph/commands/wsp/validators.py
solenya-0.1.11.dist-info/LICENSE.txt
solenya-0.1.11.dist-info/METADATA
solenya-0.1.11.dist-info/WHEEL
solenya-0.1.11.dist-info/entry_points.txt
solenya-0.1.11.dist-info/top_level.txt
solenya-0.1.11.dist-info/RECORD
