Metadata-Version: 2.1
Name: solenya
Version: 0.1.11
Summary: Microsoft365 Device Code Phishing Framework
Home-page: https://github.com/CultCornholio/solenya
Author: Artur Saradzhyan, Alex Martirosyan
Author-email: cult.cornholio@gmail.com
License: UNKNOWN
Platform: UNKNOWN
Classifier: Programming Language :: Python :: 3
Classifier: License :: OSI Approved :: MIT License
Classifier: Operating System :: OS Independent
Requires-Python: >=3.6
Requires-Dist: aiohttp (==3.7.1)
Requires-Dist: peewee (==3.14.4)
Requires-Dist: colorful (==0.5.4)
